izihawa_types-0.1.4.dist-info/METADATA
izihawa_types-0.1.4.dist-info/RECORD
izihawa_types-0.1.4.dist-info/WHEEL
izihawa_types/__init__.py
izihawa_types/datetime.py
izihawa_types/safecast.py
izihawa_types/var.py
