Metadata-Version: 2.1
Name: izihawa-types
Version: 0.1.4
Author: Pasha Podolsky
Author-email: ppodolsky@me.com
Home-page: https://github.com/izihawa/types
License: MIT License
Classifier: Topic :: Utilities
Classifier: Programming Language :: Python :: 3.8
Requires-Python: >= 3.8
Requires-Dist: numpy >= 1.22.3
